__init__.py
ssage/__init__.py
ssage/ssage.py
ssage/backend/__init__.py
ssage/backend/base.py
ssage/backend/native.py
ssage/backend/pyrage.py
ssage/backend/python_age.py
ssage/backend/helpers/__init__.py
ssage/backend/helpers/io_helpers.py
ssage-1.5.1.dist-info/licenses/LICENSE.txt
ssage-1.5.1.dist-info/METADATA
ssage-1.5.1.dist-info/WHEEL
ssage-1.5.1.dist-info/top_level.txt
ssage-1.5.1.dist-info/RECORD
