Metadata-Version: 2.4
Name: ssage
Version: 1.5.1
Summary: Super-Simple AGE - A wrapper around python age (actually good encryption)
Author-email: Adam Hlavacek <git@adamhlavacek.com>
Project-URL: Homepage, https://github.com/esoadamo/ssage
Project-URL: Issues, https://github.com/esoadamo/ssage/issues
Classifier: Programming Language :: Python :: 3
Classifier: License :: OSI Approved :: MIT License
Classifier: Operating System :: OS Independent
License-File: LICENSE.txt
Requires-Dist: age==0.5.1
Dynamic: license-file
